kernle/__init__.py
kernle/core.py
kernle/logging_config.py
kernle/utils.py
kernle/cli/__init__.py
kernle/cli/__main__.py
kernle/cli/commands/__init__.py
kernle/cli/commands/agent.py
kernle/cli/commands/anxiety.py
kernle/cli/commands/belief.py
kernle/cli/commands/doctor.py
kernle/cli/commands/emotion.py
kernle/cli/commands/forget.py
kernle/cli/commands/helpers.py
kernle/cli/commands/identity.py
kernle/cli/commands/import_cmd.py
kernle/cli/commands/init.py
kernle/cli/commands/meta.py
kernle/cli/commands/playbook.py
kernle/cli/commands/raw.py
kernle/cli/commands/setup.py
kernle/cli/commands/stats.py
kernle/cli/commands/suggestions.py
kernle/commerce/__init__.py
kernle/commerce/config.py
kernle/commerce/cli/__init__.py
kernle/commerce/cli/job.py
kernle/commerce/cli/skills.py
kernle/commerce/cli/wallet.py
kernle/commerce/escrow/__init__.py
kernle/commerce/escrow/abi.py
kernle/commerce/escrow/events.py
kernle/commerce/escrow/service.py
kernle/commerce/jobs/__init__.py
kernle/commerce/jobs/models.py
kernle/commerce/jobs/service.py
kernle/commerce/jobs/storage.py
kernle/commerce/mcp/__init__.py
kernle/commerce/mcp/tools.py
kernle/commerce/skills/__init__.py
kernle/commerce/skills/models.py
kernle/commerce/skills/registry.py
kernle/commerce/wallet/__init__.py
kernle/commerce/wallet/models.py
kernle/commerce/wallet/service.py
kernle/commerce/wallet/storage.py
kernle/features/__init__.py
kernle/features/anxiety.py
kernle/features/emotions.py
kernle/features/forgetting.py
kernle/features/knowledge.py
kernle/features/metamemory.py
kernle/features/suggestions.py
kernle/hooks/claude-code/README.md
kernle/hooks/claude-code/settings.json
kernle/hooks/clawdbot/HOOK.md
kernle/hooks/clawdbot/README.md
kernle/hooks/clawdbot/handler.ts
kernle/importers/__init__.py
kernle/importers/clawdbot.py
kernle/importers/csv_importer.py
kernle/importers/json_importer.py
kernle/importers/markdown.py
kernle/mcp/__init__.py
kernle/mcp/server.py
kernle/storage/__init__.py
kernle/storage/base.py
kernle-0.2.2.dist-info/METADATA
kernle-0.2.2.dist-info/WHEEL
kernle-0.2.2.dist-info/entry_points.txt
kernle-0.2.2.dist-info/licenses/LICENSE
kernle-0.2.2.dist-info/RECORD
