Metadata-Version: 2.4
Name: kernle
Version: 0.2.2
Summary: Stratified memory for synthetic intelligences
Project-URL: Homepage, https://kernle.ai
Project-URL: Documentation, https://docs.kernle.ai
Project-URL: Repository, https://github.com/Emergent-Instruments/kernle
Project-URL: Issues, https://github.com/Emergent-Instruments/kernle/issues
Author-email: Emergent Instruments <hello@emergentinstruments.com>, Claire <claire@emergentinstruments.com>
License-Expression: MIT
License-File: LICENSE
Keywords: agents,ai,claude,llm,mcp,memory,synthetic-intelligence
Classifier: Development Status :: 3 - Alpha
Classifier: Intended Audience :: Developers
Classifier: License :: OSI Approved :: MIT License
Classifier: Programming Language :: Python :: 3
Classifier: Programming Language :: Python :: 3.10
Classifier: Programming Language :: Python :: 3.11
Classifier: Programming Language :: Python :: 3.12
Classifier: Topic :: Scientific/Engineering :: Artificial Intelligence
Requires-Python: >=3.10
Requires-Dist: python-dotenv>=1.0.0
Requires-Dist: sqlite-vec>=0.1.0
Provides-Extra: all
Requires-Dist: mcp>=1.0.0; extra == 'all'
Requires-Dist: sqlite-vec>=0.1.0; extra == 'all'
Requires-Dist: supabase>=2.0.0; extra == 'all'
Provides-Extra: cloud
Requires-Dist: supabase>=2.0.0; extra == 'cloud'
Provides-Extra: dev
Requires-Dist: black>=23.0; extra == 'dev'
Requires-Dist: mcp>=1.0.0; extra == 'dev'
Requires-Dist: pytest-asyncio>=0.21; extra == 'dev'
Requires-Dist: pytest-cov>=4.0; extra == 'dev'
Requires-Dist: pytest>=7.0; extra == 'dev'
Requires-Dist: ruff>=0.1; extra == 'dev'
Provides-Extra: local
Requires-Dist: sqlite-vec>=0.1.0; extra == 'local'
Provides-Extra: mcp
Requires-Dist: mcp>=1.0.0; extra == 'mcp'
